{"version": "1", "message": "ERROR: Hidden Testcases server unreachable.", "problem_id": "ads2_m3_a1_1", "user_id": "harshithaRao5", "score": {"sample": {"0": {"execution_time": 0.8135418891906738, "passed": true}, "1": {"execution_time": 0.26079297065734863, "passed": true}, "2": {"execution_time": 0.1725773811340332, "passed": true}, "3": {"execution_time": 0.16974735260009766, "passed": true}, "4": {"execution_time": 0.21822237968444824, "passed": true}, "5": {"execution_time": 0.21964216232299805, "passed": true}, "6": {"execution_time": 0.20549273490905762, "passed": true}, "7": {"execution_time": 0.20960187911987305, "passed": true}}}, "check_style_score": "0/1"}